uw_restclients_trumba-1.4.2.dist-info/licenses/LICENSE
uw_trumba/VERSION
uw_trumba/__init__.py
uw_trumba/account.py
uw_trumba/calendars.py
uw_trumba/dao.py
uw_trumba/exceptions.py
uw_trumba/models.py
uw_trumba/permissions.py
uw_trumba/test.py
uw_trumba/resources/calendar/file/calendars/sea_acad-comm.ics
uw_trumba/resources/calendar/file/calendars/sea_err.ics
uw_trumba/resources/trumba_bot/file/service/calendars.asmx/GetCalendarList.Post
uw_trumba/resources/trumba_bot/file/service/calendars.asmx/GetPermissions.Post_CalendarID_0
uw_trumba/resources/trumba_bot/file/service/calendars.asmx/GetPermissions.Post_CalendarID_1
uw_trumba/resources/trumba_bot/file/service/calendars.asmx/GetPermissions.Post_CalendarID_2
uw_trumba/resources/trumba_bot/file/service/calendars.asmx/SetPermissions_CalendarID_2_Email__uw.edu_Level_EDIT
uw_trumba/resources/trumba_bot/file/service/calendars.asmx/SetPermissions_CalendarID_2_Email_test10_uw.edu_Level_EDIT
uw_trumba/resources/trumba_bot/file/service/calendars.asmx/SetPermissions_CalendarID_2_Email_test10_uw.edu_Level_NONE
uw_trumba/resources/trumba_bot/file/service/calendars.asmx/SetPermissions_CalendarID_2_Email_test10_uw.edu_Level_PUBLISH
uw_trumba/resources/trumba_bot/file/service/calendars.asmx/SetPermissions_CalendarID_2_Email_test10_uw.edu_Level_SHOWON
uw_trumba/resources/trumba_sea/file/service/accounts.asmx/CloseEditor_Email__uw.edu
uw_trumba/resources/trumba_sea/file/service/accounts.asmx/CloseEditor_Email_test10_uw.edu
uw_trumba/resources/trumba_sea/file/service/accounts.asmx/CloseEditor_Email_test_uw.edu
uw_trumba/resources/trumba_sea/file/service/accounts.asmx/CreateEditor_Name_008_Email_test8_uw.edu_Password_
uw_trumba/resources/trumba_sea/file/service/accounts.asmx/CreateEditor_Name_010_Email__uw.edu_Password_
uw_trumba/resources/trumba_sea/file/service/accounts.asmx/CreateEditor_Name_010_Email_test10_uw.edu_Password_
uw_trumba/resources/trumba_sea/file/service/accounts.asmx/CreateEditor_Name_011_Email_test10_uw.edu_Password_
uw_restclients_trumba-1.4.2.dist-info/METADATA
uw_restclients_trumba-1.4.2.dist-info/WHEEL
uw_restclients_trumba-1.4.2.dist-info/top_level.txt
uw_restclients_trumba-1.4.2.dist-info/RECORD
