Metadata-Version: 2.4
Name: UW-RestClients-Trumba
Version: 1.4.2
Summary: A library for connecting to the Trumba API
Home-page: https://github.com/uw-it-aca/uw-restclients-trumba
Author: UW-IT T&LS
Author-email: aca-it@uw.edu
License: Apache License, Version 2.0
Classifier: Intended Audience :: Developers
Classifier: License :: OSI Approved :: Apache Software License
Classifier: Operating System :: OS Independent
Classifier: Programming Language :: Python
License-File: LICENSE
Requires-Dist: UW-RestClients-Core
Requires-Dist: lxml<5
Requires-Dist: icalendar
Dynamic: author
Dynamic: author-email
Dynamic: classifier
Dynamic: description
Dynamic: home-page
Dynamic: license
Dynamic: license-file
Dynamic: requires-dist
Dynamic: summary
